pentago/__init__.py
pentago/__main__.py
pentago/api.py
pentago/client.py
pentago/detect.py
pentago/hash.py
pentago/lang.py
pentago/response.py
pentago/update.py
pentago/utils.py
pentago-0.1.3.dist-info/licenses/LICENSE
pentago-0.1.3.dist-info/METADATA
pentago-0.1.3.dist-info/WHEEL
pentago-0.1.3.dist-info/top_level.txt
pentago-0.1.3.dist-info/RECORD
