Metadata-Version: 2.4
Name: pentago
Version: 0.1.3
Summary: Unofficial Papago API using reverse-engineered web endpoints
Home-page: https://github.com/Klypse/PentaGo
Author: Klypse
License: MIT
Project-URL: Homepage, https://github.com/Klypse/PentaGo
Project-URL: Repository, https://github.com/Klypse/PentaGo
Classifier: Programming Language :: Python :: 3
Classifier: License :: OSI Approved :: MIT License
Requires-Python: >=3.6
License-File: LICENSE
Dynamic: home-page
Dynamic: license-file
Dynamic: requires-python
